{"stat.chestOpened":49,"stat.walkOneCm":203129,"stat.useItem.minecraft.chest":3,"stat.mineBlock.minecraft.netherrack":1,"stat.leaveGame":23,"stat.mineBlock.minecraft.cobblestone":37,"stat.useItem.minecraft.cobblestone":46,"stat.mineBlock.minecraft.anvil":1,"stat.furnaceInteraction":3,"stat.mineBlock.minecraft.coal_ore":2,"stat.jump":699,"stat.swimOneCm":6215,"stat.useItem.minecraft.sand":2,"stat.fallOneCm":18988,"stat.craftItem.minecraft.gold_ingot":2,"stat.mineBlock.minecraft.chest":6,"achievement.mineWood":5,"stat.useItem.minecraft.dirt":24,"stat.sprintOneCm":48233,"achievement.exploreAllBiomes":{"value":0,"progress":["ForestHills","Forest","River","Plains","Extreme Hills"]},"achievement.openInventory":44,"stat.useItem.minecraft.egg":1,"stat.mineBlock.minecraft.glass_pane":2,"stat.damageTaken":2464,"stat.useItem.minecraft.iron_ore":2,"stat.useItem.minecraft.diamond_pickaxe":158,"stat.mineBlock.minecraft.furnace":3,"stat.mineBlock.minecraft.log":5,"stat.mineBlock.minecraft.clay":2,"stat.useItem.minecraft.golden_apple":3,"stat.flyOneCm":29654,"stat.mineBlock.minecraft.planks":2,"stat.deaths":2,"stat.drop":14,"stat.mineBlock.minecraft.leaves":4,"stat.mineBlock.minecraft.sand":3,"stat.playOneMinute":50938,"stat.mineBlock.minecraft.iron_ore":2,"stat.timeSinceDeath":4520,"stat.mineBlock.minecraft.dirt":40,"stat.mineBlock.minecraft.stone":92,"stat.diveOneCm":5725}