{"stat.chestOpened":1,"stat.killEntity.Skeleton":2,"stat.walkOneCm":106558,"achievement.openInventory":5,"stat.craftItem.minecraft.planks":8,"stat.leaveGame":1,"stat.mineBlock.minecraft.vine":1,"stat.damageTaken":665,"stat.killEntity.Spider":4,"stat.craftItem.minecraft.crafting_table":1,"stat.useItem.minecraft.apple":1,"stat.mobKills":16,"stat.mineBlock.minecraft.log":14,"stat.useItem.minecraft.porkchop":2,"stat.killEntity.Creeper":1,"stat.flyOneCm":52851,"stat.deaths":2,"stat.useItem.minecraft.mutton":1,"stat.drop":3,"stat.jump":305,"stat.swimOneCm":5036,"stat.mineBlock.minecraft.leaves":31,"stat.playOneMinute":17020,"stat.climbOneCm":663,"stat.fallOneCm":6174,"stat.useItem.minecraft.wooden_sword":59,"stat.entityKilledBy.Zombie":1,"stat.killEntity.Sheep":3,"achievement.buildWorkBench":1,"stat.entityKilledBy.Skeleton":1,"stat.damageDealt":3000,"stat.killEntity.Zombie":4,"stat.timeSinceDeath":2850,"achievement.mineWood":13,"stat.useItem.minecraft.crafting_table":1,"stat.sprintOneCm":52257,"stat.killEntity.Pig":2,"achievement.exploreAllBiomes":{"value":0,"progress":["Forest","Plains"]},"stat.mineBlock.minecraft.tallgrass":3,"stat.diveOneCm":656}